phenopedia_parser/PhenopediaParser.py
phenopedia_parser/__init__.py
phenopedia_parser-0.0.3.dist-info/LICENSE
phenopedia_parser-0.0.3.dist-info/METADATA
phenopedia_parser-0.0.3.dist-info/WHEEL
phenopedia_parser-0.0.3.dist-info/top_level.txt
phenopedia_parser-0.0.3.dist-info/RECORD
