Metadata-Version: 2.1
Name: phenopedia-parser
Version: 0.0.3
Summary: A python package to parse phenopedia data
Home-page: https://github.com/julianspaeth/PhenopediaParser
Author: Julian Späth
Author-email: spaethju@posteo.de
Project-URL: Bug Tracker, https://github.com/julianspaeth/PhenopediaParser/issues
Classifier: Programming Language :: Python :: 3
Classifier: License :: OSI Approved :: MIT License
Classifier: Operating System :: OS Independent
Requires-Python: >=3.8
License-File: LICENSE
